pypiexamplezt0898/__init__.py
pypiexamplezt0898/example.py
pypiexamplezt0898-0.0.1.dist-info/LICENSE
pypiexamplezt0898-0.0.1.dist-info/METADATA
pypiexamplezt0898-0.0.1.dist-info/WHEEL
pypiexamplezt0898-0.0.1.dist-info/top_level.txt
pypiexamplezt0898-0.0.1.dist-info/RECORD
