Metadata-Version: 2.1
Name: pypiexamplezt0898
Version: 0.0.1
Summary: A small example package
Author-email: zt <330356463@qq.com>
License: MIT License        
Project-URL: Homepage, https://github.com/zhengtong0898/pypiexample-zt0898
Classifier: Programming Language :: Python :: 3
Classifier: License :: OSI Approved :: MIT License
Classifier: Operating System :: OS Independent
Requires-Python: >=3.7
License-File: LICENSE
